coxeter/__doctest_fixtures.py
coxeter/__init__.py
coxeter/io.py
coxeter/shape_getters.py
coxeter/extern/bentley_ottmann/__init__.py
coxeter/extern/bentley_ottmann/poly_point_isect.py
coxeter/extern/polytri/__init__.py
coxeter/extern/polytri/polytri.py
coxeter/families/__init__.py
coxeter/families/common.py
coxeter/families/doi_data_repositories.py
coxeter/families/plane_shape_families.py
coxeter/families/shape_family.py
coxeter/families/tabulated_shape_family.py
coxeter/families/data/archimedean.json
coxeter/families/data/catalan.json
coxeter/families/data/johnson.json
coxeter/families/data/platonic.json
coxeter/families/data/prism_antiprism.json
coxeter/families/data/pyramid_dipyramid.json
coxeter/families/data/science1220869.json
coxeter/shapes/__init__.py
coxeter/shapes/base_classes.py
coxeter/shapes/circle.py
coxeter/shapes/convex_polygon.py
coxeter/shapes/convex_polyhedron.py
coxeter/shapes/convex_spheropolygon.py
coxeter/shapes/convex_spheropolyhedron.py
coxeter/shapes/ellipse.py
coxeter/shapes/ellipsoid.py
coxeter/shapes/polygon.py
coxeter/shapes/polyhedron.py
coxeter/shapes/sphere.py
coxeter/shapes/utils.py
coxeter-0.10.0.dist-info/LICENSE
coxeter-0.10.0.dist-info/METADATA
coxeter-0.10.0.dist-info/WHEEL
coxeter-0.10.0.dist-info/top_level.txt
coxeter-0.10.0.dist-info/RECORD
