Metadata-Version: 2.2
Name: coxeter
Version: 0.10.0
Summary: Tools for creating and manipulating shapes.
Author-email: Vyas Ramasubramani <vramasub@umich.edu>, Bradley Dice <bdice@umich.edu>, Jen Bradley <jenbrad@umich.edu>
License: BSD 3-Clause License for coxeter
Project-URL: Documentation, https://coxeter.readthedocs.io
Project-URL: Download, https://pypi.org/project/coxeter/
Project-URL: Source, https://github.com/glotzerlab/coxeter
Project-URL: Issues, https://github.com/glotzerlab/coxeter/issues
Keywords: geometry
Requires-Python: >=3.8
License-File: LICENSE
Requires-Dist: numpy>=1.19.0
Requires-Dist: rowan>=1.2.0
Requires-Dist: scipy>1.0.0
Provides-Extra: tests
Requires-Dist: hypothesis[numpy]; extra == "tests"
Requires-Dist: matplotlib; extra == "tests"
Requires-Dist: miniball; extra == "tests"
Requires-Dist: plato-draw; extra == "tests"
Requires-Dist: pytest; extra == "tests"
Requires-Dist: pytest-cov; extra == "tests"
Requires-Dist: pytest-xdist; extra == "tests"
Requires-Dist: setuptools; extra == "tests"
Requires-Dist: wheel; extra == "tests"
Provides-Extra: doc
Requires-Dist: autodocsumm; extra == "doc"
Requires-Dist: furo; extra == "doc"
Requires-Dist: jupyter; extra == "doc"
Requires-Dist: matplotlib; extra == "doc"
Requires-Dist: nbsphinx; extra == "doc"
Requires-Dist: numpy; extra == "doc"
Requires-Dist: rowan>=1.2; extra == "doc"
Requires-Dist: scipy; extra == "doc"
Requires-Dist: sphinx; extra == "doc"
Requires-Dist: sphinxcontrib-bibtex>=2.0.0; extra == "doc"
